src/__init__.py
src/cli.py
src/main.py
schema_fusion_engine-0.16.0.dist-info/METADATA
schema_fusion_engine-0.16.0.dist-info/WHEEL
schema_fusion_engine-0.16.0.dist-info/entry_points.txt
schema_fusion_engine-0.16.0.dist-info/top_level.txt
schema_fusion_engine-0.16.0.dist-info/RECORD
