Metadata-Version: 2.4
Name: schema-fusion-engine
Version: 0.16.0
Summary: Middleware implementation of EasyBDI 2.0 architecture for data virtualization and federation
Author: SchemaFusion Team
License: MIT
Keywords: data-virtualization,federation,trino,middleware,easybdi
Classifier: Development Status :: 3 - Alpha
Classifier: Intended Audience :: Developers
Classifier: Programming Language :: Python :: 3
Classifier: Programming Language :: Python :: 3.11
Classifier: Programming Language :: Python :: 3.12
Classifier: Programming Language :: Python :: 3.13
Classifier: Programming Language :: Python :: 3.14
Requires-Python: >=3.11
Requires-Dist: fastapi<1.0.0,>=0.123.8
Requires-Dist: uvicorn[standard]<1.0.0,>=0.38.0
Requires-Dist: trino<1.0.0,>=0.336.0
Requires-Dist: typer<1.0.0,>=0.20.0
Requires-Dist: python-Levenshtein<1.0.0,>=0.27.3
Requires-Dist: slowapi<1.0.0,>=0.1.9
Requires-Dist: prometheus-fastapi-instrumentator<8.0.0,>=7.0.0
Requires-Dist: redis<8.0.0,>=5.0.0
Requires-Dist: pydantic-settings<3.0.0,>=2.0.0
Requires-Dist: httpx<1.0.0,>=0.27.0
Requires-Dist: PyJWT<3.0.0,>=2.8.0
Requires-Dist: sqlalchemy<3.0.0,>=2.0.0
Requires-Dist: psycopg2-binary<3.0.0,>=2.9.0
Requires-Dist: pymysql<2.0.0,>=1.0.0
Requires-Dist: pymongo<5.0.0,>=4.0.0
Requires-Dist: kafka-python<3.0.0,>=2.0.0
Requires-Dist: redis<8.0.0,>=5.0.0
Provides-Extra: dev
Requires-Dist: pytest>=7.0.0; extra == "dev"
Requires-Dist: pytest-asyncio>=0.21.0; extra == "dev"
Requires-Dist: pytest-cov>=4.0.0; extra == "dev"
Requires-Dist: ruff>=0.1.0; extra == "dev"
Requires-Dist: black>=23.0.0; extra == "dev"
Requires-Dist: mypy>=1.0.0; extra == "dev"
Requires-Dist: types-PyMySQL>=1.0.0; extra == "dev"
